.gitignore
README.rst
requirements.txt
setup.py
stdin2sftp
src/stdin2sftp/__init__.py
src/stdin2sftp/main.py
stdin2sftp.egg-info/PKG-INFO
stdin2sftp.egg-info/SOURCES.txt
stdin2sftp.egg-info/dependency_links.txt
stdin2sftp.egg-info/entry_points.txt
stdin2sftp.egg-info/requires.txt
stdin2sftp.egg-info/top_level.txt