Metadata-Version: 2.1
Name: stdin2sftp
Version: 0.1.0
Summary: stdin to sftp pump
Home-page: https://github.com/slashbeast/stdin2sftp
Author: Piotr Karbowski
License: BSD
Download-URL: https://github.com/slashbeast/stdin2sftp/archive/v0.1.0.tar.gz
Platform: UNKNOWN
